

{
  "itemIdentifier": "surround.demo.3dcadastre.topo-polyhedron",
  "name": "Polydron using nested Polygons and Point topology",
  "abstract": "Defines options for describing 3D polyhedrons using features with Point geometry coordinates",
  "status": "under-development",
  "dateTimeAddition": "2023-11-01T00:00:00Z",
  "itemClass": "schema",
  "register": "ogcincubator",
  "version": "0.1",
  "dateOfLastChange": "2024-07-22",
  "sources": [],
  "maturity": "development",
  "scope": "unstable",
  "tags": [
    "3D",
    "geometry",
    "topology"
  ],
  "shaclRules": {
    "ogc.geo.topo.features.topo-feature": [
      "https://ogcincubator.github.io/topo-feature/_sources/features/topo-feature-collection/tests/topo-refs-exist.shacl",
      "https://ogcincubator.github.io/topo-feature/_sources/features/topo-feature/tests/geometry-coordinates.shacl"
    ],
    "ogc.geo.topo.features.topo-feature-collection": [
      "https://ogcincubator.github.io/topo-feature/_sources/features/topo-feature-collection/tests/topo-refs-exist.shacl",
      "https://ogcincubator.github.io/topo-feature/_sources/features/topo-feature/tests/geometry-coordinates.shacl"
    ]
  },
  "shaclClosures": [],
  "dependsOn": [
    "ogc.geo.topo.datatypes.topology",
    "ogc.geo.topo.features.topo-feature",
    "ogc.geo.features.featureCollection",
    "ogc.geo.topo.features.topo-feature-collection"
  ],
  "ldContext": "https://surroundaustralia.github.io/wa-3d-cadastre-demo/build/annotated/demo/3dcadastre/topo-polyhedron/context.jsonld",
  "schema": {
    "application/yaml": "https://surroundaustralia.github.io/wa-3d-cadastre-demo/build/annotated/demo/3dcadastre/topo-polyhedron/schema.yaml",
    "application/json": "https://surroundaustralia.github.io/wa-3d-cadastre-demo/build/annotated/demo/3dcadastre/topo-polyhedron/schema.json"
  },
  "sourceSchema": "https://surroundaustralia.github.io/wa-3d-cadastre-demo/_sources/topo-polyhedron/schema.json",
  "sourceLdContext": "https://surroundaustralia.github.io/wa-3d-cadastre-demo/_sources/topo-polyhedron/context.jsonld",
  "sourceFiles": "https://surroundaustralia.github.io/wa-3d-cadastre-demo/_sources/topo-polyhedron/",
  "validationPassed": true,
  "testOutputs": "https://github.com/surroundaustralia/wa-3d-cadastre-demo/blob/master/build/tests/demo/3dcadastre/topo-polyhedron/",
  "description": "## Topology defining Polyhedrons\n\nA feature type using a topology property to reference points defining Polyhedrons as per the FG-JSON extended geometry model\n\n\n\n",
  "examples": [
    {
      "title": "Example GeoJSON feature using",
      "content": "3D Polyhedron example",
      "snippets": [
        {
          "language": "json",
          "base-uri": "http://www.example.com/features/",
          "ref": "examples/building_topo.json",
          "code": "{\n  \"type\": \"FeatureCollection\",\n  \"features\": [\n    {\n      \"type\": \"Feature\",\n      \"id\": \"P479816.67_5705861.672_100\",\n      \"geometry\": {\n        \"type\": \"Point\",\n        \"coordinates\": [\n          479816.67,\n          5705861.672,\n          100\n        ]\n      },\n      \"properties\": {}\n    },\n    {\n      \"type\": \"Feature\",\n      \"id\": \"P479822.187_5705866.783_100\",\n      \"geometry\": {\n        \"type\": \"Point\",\n        \"coordinates\": [\n          479822.187,\n          5705866.783,\n          100\n        ]\n      },\n      \"properties\": {}\n    },\n    {\n      \"type\": \"Feature\",\n      \"id\": \"P479829.666_5705858.785_100\",\n      \"geometry\": {\n        \"type\": \"Point\",\n        \"coordinates\": [\n          479829.666,\n          5705858.785,\n          100\n        ]\n      },\n      \"properties\": {}\n    },\n    {\n      \"type\": \"Feature\",\n      \"id\": \"P479824.155_5705853.684_100\",\n      \"geometry\": {\n        \"type\": \"Point\",\n        \"coordinates\": [\n          479824.155,\n          5705853.684,\n          100\n        ]\n      },\n      \"properties\": {}\n    },\n    {\n      \"type\": \"Feature\",\n      \"id\": \"P479816.67_5705861.672_110\",\n      \"geometry\": {\n        \"type\": \"Point\",\n        \"coordinates\": [\n          479816.67,\n          5705861.672,\n          110\n        ]\n      },\n      \"properties\": {}\n    },\n    {\n      \"type\": \"Feature\",\n      \"id\": \"P479824.155_5705853.684_110\",\n      \"geometry\": {\n        \"type\": \"Point\",\n        \"coordinates\": [\n          479824.155,\n          5705853.684,\n          110\n        ]\n      },\n      \"properties\": {}\n    },\n    {\n      \"type\": \"Feature\",\n      \"id\": \"P479829.666_5705858.785_120\",\n      \"geometry\": {\n        \"type\": \"Point\",\n        \"coordinates\": [\n          479829.666,\n          5705858.785,\n          120\n        ]\n      },\n      \"properties\": {}\n    },\n    {\n      \"type\": \"Feature\",\n      \"id\": \"P479822.187_5705866.783_120\",\n      \"geometry\": {\n        \"type\": \"Point\",\n        \"coordinates\": [\n          479822.187,\n          5705866.783,\n          120\n        ]\n      },\n      \"properties\": {}\n    },\n    {\n      \"type\": \"Feature\",\n      \"id\": \"DENW19AL0000giv5BL\",\n      \"conformsTo\": [\n        \"[ogc-json-fg-1-0.2:core]\",\n        \"[ogc-json-fg-1-0.2:types-schemas]\",\n        \"[ogc-json-fg-1-0.2:3d]\"\n      ],\n      \"featureType\": \"app:building\",\n      \"featureSchema\": \"https://example.org/data/v1/collections/buildings/schema\",\n      \"time\": {\n        \"interval\": [\n          \"2014-04-24T10:50:18Z\",\n          \"..\"\n        ]\n      },\n      \"coordRefSys\": \"http://www.opengis.net/def/crs/EPSG/0/5555\",\n      \"place\": {\n        \"type\": \"Polyhedron\",\n        \"coordinates\": [\n          [\n            [\n              [\n                [\n                  479816.67,\n                  5705861.672,\n                  100\n                ],\n                [\n                  479822.187,\n                  5705866.783,\n                  100\n                ],\n                [\n                  479829.666,\n                  5705858.785,\n                  100\n                ],\n                [\n                  479824.155,\n                  5705853.684,\n                  100\n                ],\n                [\n                  479816.67,\n                  5705861.672,\n                  100\n                ]\n              ]\n            ],\n            [\n              [\n                [\n                  479816.67,\n                  5705861.672,\n                  110\n                ],\n                [\n                  479824.155,\n                  5705853.684,\n                  110\n                ],\n                [\n                  479829.666,\n                  5705858.785,\n                  120\n                ],\n                [\n                  479822.187,\n                  5705866.783,\n                  120\n                ],\n                [\n                  479816.67,\n                  5705861.672,\n                  110\n                ]\n              ]\n            ],\n            [\n              [\n                [\n                  479816.67,\n                  5705861.672,\n                  110\n                ],\n                [\n                  479816.67,\n                  5705861.672,\n                  100\n                ],\n                [\n                  479824.155,\n                  5705853.684,\n                  100\n                ],\n                [\n                  479824.155,\n                  5705853.684,\n                  110\n                ],\n                [\n                  479816.67,\n                  5705861.672,\n                  110\n                ]\n              ]\n            ],\n            [\n              [\n                [\n                  479824.155,\n                  5705853.684,\n                  110\n                ],\n                [\n                  479824.155,\n                  5705853.684,\n                  100\n                ],\n                [\n                  479829.666,\n                  5705858.785,\n                  100\n                ],\n                [\n                  479829.666,\n                  5705858.785,\n                  120\n                ],\n                [\n                  479824.155,\n                  5705853.684,\n                  110\n                ]\n              ]\n            ],\n            [\n              [\n                [\n                  479829.666,\n                  5705858.785,\n                  120\n                ],\n                [\n                  479829.666,\n                  5705858.785,\n                  100\n                ],\n                [\n                  479822.187,\n                  5705866.783,\n                  100\n                ],\n                [\n                  479822.187,\n                  5705866.783,\n                  120\n                ],\n                [\n                  479829.666,\n                  5705858.785,\n                  120\n                ]\n              ]\n            ],\n            [\n              [\n                [\n                  479822.187,\n                  5705866.783,\n                  120\n                ],\n                [\n                  479822.187,\n                  5705866.783,\n                  100\n                ],\n                [\n                  479816.67,\n                  5705861.672,\n                  100\n                ],\n                [\n                  479816.67,\n                  5705861.672,\n                  110\n                ],\n                [\n                  479822.187,\n                  5705866.783,\n                  120\n                ]\n              ]\n            ]\n          ]\n        ]\n      },\n      \"geometry\": {\n        \"type\": \"Polygon\",\n        \"coordinates\": [\n          [\n            [\n              8.7092045,\n              51.5035285,\n              100\n            ],\n            [\n              8.7093128,\n              51.503457,\n              100\n            ],\n            [\n              8.7093919,\n              51.503503,\n              100\n            ],\n            [\n              8.7092837,\n              51.5035747,\n              100\n            ],\n            [\n              8.7092045,\n              51.5035285,\n              100\n            ]\n          ]\n        ]\n      },\n      \"links\": [\n        {\n          \"href\": \"https://example.org/data/v1/collections/cadastralparcel/items/05297001600313______\",\n          \"rel\": \"http://www.opengis.net/def/rel/ogc/1.0/within\",\n          \"title\": \"Cadastral parcel 313 in district W\\u00c3\\u00bcnnenberg (016)\"\n        },\n        {\n          \"href\": \"https://inspire.ec.europa.eu/featureconcept/Building\",\n          \"rel\": \"type\",\n          \"title\": \"This feature is of type 'building'\"\n        }\n      ],\n      \"properties\": {\n        \"lastChange\": \"2014-04-24T10:50:18Z\",\n        \"built\": \"2012-03\",\n        \"function\": \"Agricultural building\",\n        \"height_m\": 20.0,\n        \"owners\": [\n          {\n            \"href\": \"https://example.org/john-doe\",\n            \"title\": \"John Doe\"\n          },\n          {\n            \"href\": \"https://example.org/jane-doe\",\n            \"title\": \"Jane Doe\"\n          }\n        ]\n      },\n      \"topology\": {\n        \"type\": \"Polyhedron\",\n        \"references\": [\n          [\n            [\n              [\n                \"P479816.67_5705861.672_100\",\n                \"P479822.187_5705866.783_100\",\n                \"P479829.666_5705858.785_100\",\n                \"P479824.155_5705853.684_100\",\n                \"P479816.67_5705861.672_100\"\n              ]\n            ],\n            [\n              [\n                \"P479816.67_5705861.672_110\",\n                \"P479824.155_5705853.684_110\",\n                \"P479829.666_5705858.785_120\",\n                \"P479822.187_5705866.783_120\",\n                \"P479816.67_5705861.672_110\"\n              ]\n            ],\n            [\n              [\n                \"P479816.67_5705861.672_110\",\n                \"P479816.67_5705861.672_100\",\n                \"P479824.155_5705853.684_100\",\n                \"P479824.155_5705853.684_110\",\n                \"P479816.67_5705861.672_110\"\n              ]\n            ],\n            [\n              [\n                \"P479824.155_5705853.684_110\",\n                \"P479824.155_5705853.684_100\",\n                \"P479829.666_5705858.785_100\",\n                \"P479829.666_5705858.785_120\",\n                \"P479824.155_5705853.684_110\"\n              ]\n            ],\n            [\n              [\n                \"P479829.666_5705858.785_120\",\n                \"P479829.666_5705858.785_100\",\n                \"P479822.187_5705866.783_100\",\n                \"P479822.187_5705866.783_120\",\n                \"P479829.666_5705858.785_120\"\n              ]\n            ],\n            [\n              [\n                \"P479822.187_5705866.783_120\",\n                \"P479822.187_5705866.783_100\",\n                \"P479816.67_5705861.672_100\",\n                \"P479816.67_5705861.672_110\",\n                \"P479822.187_5705866.783_120\"\n              ]\n            ]\n          ]\n        ]\n      }\n    }\n  ]\n}",
          "url": "https://surroundaustralia.github.io/wa-3d-cadastre-demo/build/tests/demo/3dcadastre/topo-polyhedron/example_1_1.json"
        },
        {
          "language": "jsonld",
          "code": "{\n  \"type\": \"FeatureCollection\",\n  \"features\": [\n    {\n      \"type\": \"Feature\",\n      \"id\": \"P479816.67_5705861.672_100\",\n      \"geometry\": {\n        \"type\": \"Point\",\n        \"coordinates\": [\n          479816.67,\n          5705861.672,\n          100\n        ]\n      },\n      \"properties\": {}\n    },\n    {\n      \"type\": \"Feature\",\n      \"id\": \"P479822.187_5705866.783_100\",\n      \"geometry\": {\n        \"type\": \"Point\",\n        \"coordinates\": [\n          479822.187,\n          5705866.783,\n          100\n        ]\n      },\n      \"properties\": {}\n    },\n    {\n      \"type\": \"Feature\",\n      \"id\": \"P479829.666_5705858.785_100\",\n      \"geometry\": {\n        \"type\": \"Point\",\n        \"coordinates\": [\n          479829.666,\n          5705858.785,\n          100\n        ]\n      },\n      \"properties\": {}\n    },\n    {\n      \"type\": \"Feature\",\n      \"id\": \"P479824.155_5705853.684_100\",\n      \"geometry\": {\n        \"type\": \"Point\",\n        \"coordinates\": [\n          479824.155,\n          5705853.684,\n          100\n        ]\n      },\n      \"properties\": {}\n    },\n    {\n      \"type\": \"Feature\",\n      \"id\": \"P479816.67_5705861.672_110\",\n      \"geometry\": {\n        \"type\": \"Point\",\n        \"coordinates\": [\n          479816.67,\n          5705861.672,\n          110\n        ]\n      },\n      \"properties\": {}\n    },\n    {\n      \"type\": \"Feature\",\n      \"id\": \"P479824.155_5705853.684_110\",\n      \"geometry\": {\n        \"type\": \"Point\",\n        \"coordinates\": [\n          479824.155,\n          5705853.684,\n          110\n        ]\n      },\n      \"properties\": {}\n    },\n    {\n      \"type\": \"Feature\",\n      \"id\": \"P479829.666_5705858.785_120\",\n      \"geometry\": {\n        \"type\": \"Point\",\n        \"coordinates\": [\n          479829.666,\n          5705858.785,\n          120\n        ]\n      },\n      \"properties\": {}\n    },\n    {\n      \"type\": \"Feature\",\n      \"id\": \"P479822.187_5705866.783_120\",\n      \"geometry\": {\n        \"type\": \"Point\",\n        \"coordinates\": [\n          479822.187,\n          5705866.783,\n          120\n        ]\n      },\n      \"properties\": {}\n    },\n    {\n      \"type\": \"Feature\",\n      \"id\": \"DENW19AL0000giv5BL\",\n      \"conformsTo\": [\n        \"[ogc-json-fg-1-0.2:core]\",\n        \"[ogc-json-fg-1-0.2:types-schemas]\",\n        \"[ogc-json-fg-1-0.2:3d]\"\n      ],\n      \"featureType\": \"app:building\",\n      \"featureSchema\": \"https://example.org/data/v1/collections/buildings/schema\",\n      \"time\": {\n        \"interval\": [\n          \"2014-04-24T10:50:18Z\",\n          \"..\"\n        ]\n      },\n      \"coordRefSys\": \"http://www.opengis.net/def/crs/EPSG/0/5555\",\n      \"place\": {\n        \"type\": \"Polyhedron\",\n        \"coordinates\": [\n          [\n            [\n              [\n                [\n                  479816.67,\n                  5705861.672,\n                  100\n                ],\n                [\n                  479822.187,\n                  5705866.783,\n                  100\n                ],\n                [\n                  479829.666,\n                  5705858.785,\n                  100\n                ],\n                [\n                  479824.155,\n                  5705853.684,\n                  100\n                ],\n                [\n                  479816.67,\n                  5705861.672,\n                  100\n                ]\n              ]\n            ],\n            [\n              [\n                [\n                  479816.67,\n                  5705861.672,\n                  110\n                ],\n                [\n                  479824.155,\n                  5705853.684,\n                  110\n                ],\n                [\n                  479829.666,\n                  5705858.785,\n                  120\n                ],\n                [\n                  479822.187,\n                  5705866.783,\n                  120\n                ],\n                [\n                  479816.67,\n                  5705861.672,\n                  110\n                ]\n              ]\n            ],\n            [\n              [\n                [\n                  479816.67,\n                  5705861.672,\n                  110\n                ],\n                [\n                  479816.67,\n                  5705861.672,\n                  100\n                ],\n                [\n                  479824.155,\n                  5705853.684,\n                  100\n                ],\n                [\n                  479824.155,\n                  5705853.684,\n                  110\n                ],\n                [\n                  479816.67,\n                  5705861.672,\n                  110\n                ]\n              ]\n            ],\n            [\n              [\n                [\n                  479824.155,\n                  5705853.684,\n                  110\n                ],\n                [\n                  479824.155,\n                  5705853.684,\n                  100\n                ],\n                [\n                  479829.666,\n                  5705858.785,\n                  100\n                ],\n                [\n                  479829.666,\n                  5705858.785,\n                  120\n                ],\n                [\n                  479824.155,\n                  5705853.684,\n                  110\n                ]\n              ]\n            ],\n            [\n              [\n                [\n                  479829.666,\n                  5705858.785,\n                  120\n                ],\n                [\n                  479829.666,\n                  5705858.785,\n                  100\n                ],\n                [\n                  479822.187,\n                  5705866.783,\n                  100\n                ],\n                [\n                  479822.187,\n                  5705866.783,\n                  120\n                ],\n                [\n                  479829.666,\n                  5705858.785,\n                  120\n                ]\n              ]\n            ],\n            [\n              [\n                [\n                  479822.187,\n                  5705866.783,\n                  120\n                ],\n                [\n                  479822.187,\n                  5705866.783,\n                  100\n                ],\n                [\n                  479816.67,\n                  5705861.672,\n                  100\n                ],\n                [\n                  479816.67,\n                  5705861.672,\n                  110\n                ],\n                [\n                  479822.187,\n                  5705866.783,\n                  120\n                ]\n              ]\n            ]\n          ]\n        ]\n      },\n      \"geometry\": {\n        \"type\": \"Polygon\",\n        \"coordinates\": [\n          [\n            [\n              8.7092045,\n              51.5035285,\n              100\n            ],\n            [\n              8.7093128,\n              51.503457,\n              100\n            ],\n            [\n              8.7093919,\n              51.503503,\n              100\n            ],\n            [\n              8.7092837,\n              51.5035747,\n              100\n            ],\n            [\n              8.7092045,\n              51.5035285,\n              100\n            ]\n          ]\n        ]\n      },\n      \"links\": [\n        {\n          \"href\": \"https://example.org/data/v1/collections/cadastralparcel/items/05297001600313______\",\n          \"rel\": \"http://www.opengis.net/def/rel/ogc/1.0/within\",\n          \"title\": \"Cadastral parcel 313 in district W\\u00c3\\u00bcnnenberg (016)\"\n        },\n        {\n          \"href\": \"https://inspire.ec.europa.eu/featureconcept/Building\",\n          \"rel\": \"type\",\n          \"title\": \"This feature is of type 'building'\"\n        }\n      ],\n      \"properties\": {\n        \"lastChange\": \"2014-04-24T10:50:18Z\",\n        \"built\": \"2012-03\",\n        \"function\": \"Agricultural building\",\n        \"height_m\": 20.0,\n        \"owners\": [\n          {\n            \"href\": \"https://example.org/john-doe\",\n            \"title\": \"John Doe\"\n          },\n          {\n            \"href\": \"https://example.org/jane-doe\",\n            \"title\": \"Jane Doe\"\n          }\n        ]\n      },\n      \"topology\": {\n        \"type\": \"Polyhedron\",\n        \"references\": [\n          [\n            [\n              [\n                \"P479816.67_5705861.672_100\",\n                \"P479822.187_5705866.783_100\",\n                \"P479829.666_5705858.785_100\",\n                \"P479824.155_5705853.684_100\",\n                \"P479816.67_5705861.672_100\"\n              ]\n            ],\n            [\n              [\n                \"P479816.67_5705861.672_110\",\n                \"P479824.155_5705853.684_110\",\n                \"P479829.666_5705858.785_120\",\n                \"P479822.187_5705866.783_120\",\n                \"P479816.67_5705861.672_110\"\n              ]\n            ],\n            [\n              [\n                \"P479816.67_5705861.672_110\",\n                \"P479816.67_5705861.672_100\",\n                \"P479824.155_5705853.684_100\",\n                \"P479824.155_5705853.684_110\",\n                \"P479816.67_5705861.672_110\"\n              ]\n            ],\n            [\n              [\n                \"P479824.155_5705853.684_110\",\n                \"P479824.155_5705853.684_100\",\n                \"P479829.666_5705858.785_100\",\n                \"P479829.666_5705858.785_120\",\n                \"P479824.155_5705853.684_110\"\n              ]\n            ],\n            [\n              [\n                \"P479829.666_5705858.785_120\",\n                \"P479829.666_5705858.785_100\",\n                \"P479822.187_5705866.783_100\",\n                \"P479822.187_5705866.783_120\",\n                \"P479829.666_5705858.785_120\"\n              ]\n            ],\n            [\n              [\n                \"P479822.187_5705866.783_120\",\n                \"P479822.187_5705866.783_100\",\n                \"P479816.67_5705861.672_100\",\n                \"P479816.67_5705861.672_110\",\n                \"P479822.187_5705866.783_120\"\n              ]\n            ]\n          ]\n        ]\n      }\n    }\n  ],\n  \"@context\": \"https://surroundaustralia.github.io/wa-3d-cadastre-demo/build/annotated/demo/3dcadastre/topo-polyhedron/context.jsonld\"\n}",
          "url": "https://surroundaustralia.github.io/wa-3d-cadastre-demo/build/tests/demo/3dcadastre/topo-polyhedron/example_1_1.jsonld"
        },
        {
          "language": "ttl",
          "code": "@prefix dcterms: <http://purl.org/dc/terms/> .\n@prefix geojson: <https://purl.org/geojson/vocab#> .\n@prefix ns1: <http://www.iana.org/assignments/> .\n@prefix ns2: <http://www.opengis.net/def/glossary/term/> .\n@prefix oa: <http://www.w3.org/ns/oa#> .\n@prefix rdf: <http://www.w3.org/1999/02/22-rdf-syntax-ns#> .\n@prefix rdfs: <http://www.w3.org/2000/01/rdf-schema#> .\n@prefix time: <http://www.w3.org/2006/time#> .\n@prefix xsd: <http://www.w3.org/2001/XMLSchema#> .\n\n<http://www.example.com/features/DENW19AL0000giv5BL> a <app:building>,\n        geojson:Feature ;\n    dcterms:spatial [ a geojson:Polyhedron ;\n            geojson:coordinates ( ( ( ( ( 4.798167e+05 5.705862e+06 100 ) ( 4.798222e+05 5.705867e+06 100 ) ( 4.798297e+05 5.705859e+06 100 ) ( 4.798242e+05 5.705854e+06 100 ) ( 4.798167e+05 5.705862e+06 100 ) ) ) ( ( ( 4.798167e+05 5.705862e+06 110 ) ( 4.798242e+05 5.705854e+06 110 ) ( 4.798297e+05 5.705859e+06 120 ) ( 4.798222e+05 5.705867e+06 120 ) ( 4.798167e+05 5.705862e+06 110 ) ) ) ( ( ( 4.798167e+05 5.705862e+06 110 ) ( 4.798167e+05 5.705862e+06 100 ) ( 4.798242e+05 5.705854e+06 100 ) ( 4.798242e+05 5.705854e+06 110 ) ( 4.798167e+05 5.705862e+06 110 ) ) ) ( ( ( 4.798242e+05 5.705854e+06 110 ) ( 4.798242e+05 5.705854e+06 100 ) ( 4.798297e+05 5.705859e+06 100 ) ( 4.798297e+05 5.705859e+06 120 ) ( 4.798242e+05 5.705854e+06 110 ) ) ) ( ( ( 4.798297e+05 5.705859e+06 120 ) ( 4.798297e+05 5.705859e+06 100 ) ( 4.798222e+05 5.705867e+06 100 ) ( 4.798222e+05 5.705867e+06 120 ) ( 4.798297e+05 5.705859e+06 120 ) ) ) ( ( ( 4.798222e+05 5.705867e+06 120 ) ( 4.798222e+05 5.705867e+06 100 ) ( 4.798167e+05 5.705862e+06 100 ) ( 4.798167e+05 5.705862e+06 110 ) ( 4.798222e+05 5.705867e+06 120 ) ) ) ) ) ] ;\n    dcterms:time [ time:hasTime ( \"2014-04-24T10:50:18Z\" \"..\" ) ] ;\n    ns2:CoordinateReferenceSystemCRS \"http://www.opengis.net/def/crs/EPSG/0/5555\" ;\n    rdfs:seeAlso [ rdfs:label \"Cadastral parcel 313 in district W\u00c3\u00bcnnenberg (016)\" ;\n            ns1:relation <http://www.opengis.net/def/rel/ogc/1.0/within> ;\n            oa:hasTarget <https://example.org/data/v1/collections/cadastralparcel/items/05297001600313______> ],\n        [ rdfs:label \"This feature is of type 'building'\" ;\n            ns1:relation <http://www.iana.org/assignments/relation/type> ;\n            oa:hasTarget <https://inspire.ec.europa.eu/featureconcept/Building> ] ;\n    geojson:geometry [ a geojson:Polygon ;\n            geojson:coordinates ( ( ( 8.709205e+00 5.150353e+01 100 ) ( 8.709313e+00 5.150346e+01 100 ) ( 8.709392e+00 5.15035e+01 100 ) ( 8.709284e+00 5.150357e+01 100 ) ( 8.709205e+00 5.150353e+01 100 ) ) ) ] ;\n    geojson:topology [ a geojson:Polyhedron ;\n            geojson:relatedFeatures ( ( ( ( <http://www.example.com/features/P479816.67_5705861.672_100> <http://www.example.com/features/P479822.187_5705866.783_100> <http://www.example.com/features/P479829.666_5705858.785_100> <http://www.example.com/features/P479824.155_5705853.684_100> <http://www.example.com/features/P479816.67_5705861.672_100> ) ) ( ( <http://www.example.com/features/P479816.67_5705861.672_110> <http://www.example.com/features/P479824.155_5705853.684_110> <http://www.example.com/features/P479829.666_5705858.785_120> <http://www.example.com/features/P479822.187_5705866.783_120> <http://www.example.com/features/P479816.67_5705861.672_110> ) ) ( ( <http://www.example.com/features/P479816.67_5705861.672_110> <http://www.example.com/features/P479816.67_5705861.672_100> <http://www.example.com/features/P479824.155_5705853.684_100> <http://www.example.com/features/P479824.155_5705853.684_110> <http://www.example.com/features/P479816.67_5705861.672_110> ) ) ( ( <http://www.example.com/features/P479824.155_5705853.684_110> <http://www.example.com/features/P479824.155_5705853.684_100> <http://www.example.com/features/P479829.666_5705858.785_100> <http://www.example.com/features/P479829.666_5705858.785_120> <http://www.example.com/features/P479824.155_5705853.684_110> ) ) ( ( <http://www.example.com/features/P479829.666_5705858.785_120> <http://www.example.com/features/P479829.666_5705858.785_100> <http://www.example.com/features/P479822.187_5705866.783_100> <http://www.example.com/features/P479822.187_5705866.783_120> <http://www.example.com/features/P479829.666_5705858.785_120> ) ) ( ( <http://www.example.com/features/P479822.187_5705866.783_120> <http://www.example.com/features/P479822.187_5705866.783_100> <http://www.example.com/features/P479816.67_5705861.672_100> <http://www.example.com/features/P479816.67_5705861.672_110> <http://www.example.com/features/P479822.187_5705866.783_120> ) ) ) ) ] .\n\n<http://www.example.com/features/P479822.187_5705866.783_100> a geojson:Feature ;\n    geojson:geometry [ a geojson:Point ;\n            geojson:coordinates ( 4.798222e+05 5.705867e+06 100 ) ] .\n\n<http://www.example.com/features/P479824.155_5705853.684_100> a geojson:Feature ;\n    geojson:geometry [ a geojson:Point ;\n            geojson:coordinates ( 4.798242e+05 5.705854e+06 100 ) ] .\n\n<http://www.example.com/features/P479829.666_5705858.785_100> a geojson:Feature ;\n    geojson:geometry [ a geojson:Point ;\n            geojson:coordinates ( 4.798297e+05 5.705859e+06 100 ) ] .\n\n<http://www.example.com/features/P479816.67_5705861.672_100> a geojson:Feature ;\n    geojson:geometry [ a geojson:Point ;\n            geojson:coordinates ( 4.798167e+05 5.705862e+06 100 ) ] .\n\n<http://www.example.com/features/P479822.187_5705866.783_120> a geojson:Feature ;\n    geojson:geometry [ a geojson:Point ;\n            geojson:coordinates ( 4.798222e+05 5.705867e+06 120 ) ] .\n\n<http://www.example.com/features/P479824.155_5705853.684_110> a geojson:Feature ;\n    geojson:geometry [ a geojson:Point ;\n            geojson:coordinates ( 4.798242e+05 5.705854e+06 110 ) ] .\n\n<http://www.example.com/features/P479829.666_5705858.785_120> a geojson:Feature ;\n    geojson:geometry [ a geojson:Point ;\n            geojson:coordinates ( 4.798297e+05 5.705859e+06 120 ) ] .\n\n<http://www.example.com/features/P479816.67_5705861.672_110> a geojson:Feature ;\n    geojson:geometry [ a geojson:Point ;\n            geojson:coordinates ( 4.798167e+05 5.705862e+06 110 ) ] .\n\n[] a geojson:FeatureCollection ;\n    geojson:features <http://www.example.com/features/DENW19AL0000giv5BL>,\n        <http://www.example.com/features/P479816.67_5705861.672_100>,\n        <http://www.example.com/features/P479816.67_5705861.672_110>,\n        <http://www.example.com/features/P479822.187_5705866.783_100>,\n        <http://www.example.com/features/P479822.187_5705866.783_120>,\n        <http://www.example.com/features/P479824.155_5705853.684_100>,\n        <http://www.example.com/features/P479824.155_5705853.684_110>,\n        <http://www.example.com/features/P479829.666_5705858.785_100>,\n        <http://www.example.com/features/P479829.666_5705858.785_120> .\n\n",
          "url": "https://surroundaustralia.github.io/wa-3d-cadastre-demo/build/tests/demo/3dcadastre/topo-polyhedron/example_1_1.ttl"
        }
      ]
    }
  ],
  "annotatedSchema": "$schema: https://json-schema.org/draft/2020-12/schema\ndescription: Arc Feature with geometry by reference\n$defs:\n  PolyhedralFeature:\n    allOf:\n    - $ref: https://ogcincubator.github.io/topo-feature/build/annotated/geo/topo/features/topo-feature/schema.yaml\n    - properties:\n        topology:\n          allOf:\n          - $ref: https://ogcincubator.github.io/topo-feature/build/annotated/geo/topo/datatypes/topology/schema.yaml\n          - oneOf:\n            - properties:\n                type:\n                  type: string\n                  const: Polyhedron\n                references:\n                  type: array\n      required:\n      - topology\n  ContainedFeatureCollection:\n    anyOf:\n    - $ref: https://ogcincubator.github.io/topo-feature/build/annotated/geo/topo/features/topo-feature-collection/schema.yaml\n    - $ref: https://opengeospatial.github.io/bblocks/annotated-schemas/geo/features/featureCollection/schema.yaml\noneOf:\n- $ref: '#/$defs/PolyhedralFeature'\n- $ref: '#/$defs/ContainedFeatureCollection'\n",
  "gitRepository": "https://github.com/surroundaustralia/wa-3d-cadastre-demo",
  "gitPath": "_sources/topo-polyhedron"
}